{
  "cli": {
    "version": ">= 13.0.0",
    "appVersionSource": "remote"
  },
  "build": {
    "development": {
      "developmentClient": true,
      "distribution": "internal",
      "android": {
        "gradleCommand": ":app:assembleDebug"
      },
      "ios": {
        "simulator": true
      }
    },
    "preview": {
      "distribution": "internal",
      "android": {
        "buildType": "apk"
      },
      "ios": {
        "resourceClass": "m-medium"
      },
      "env": {
        "EXPO_PUBLIC_API_ENV": "preview"
      }
    },
    "production": {
      "distribution": "store",
      "android": {
        "buildType": "app-bundle"
      },
      "ios": {
        "resourceClass": "m-medium"
      },
      "env": {
        "EXPO_PUBLIC_API_ENV": "production"
      },
      "autoIncrement": true
    }
  },
  "submit": {
    "production": {
      "android": {
        "serviceAccountKeyPath": "./google-service-account.json",
        "track": "internal",
        "releaseStatus": "draft"
      },
      "ios": {
        "appleId": "your-apple-id@email.com",
        "ascAppId": "your-asc-app-id",
        "appleTeamId": "your-team-id"
      }
    }
  }
}
